.gitignore
MANIFEST.in
README.md
setup.py
algospace/__init__.py
algospace/__main__.py
algospace/config.py
algospace/logger.py
algospace/login.py
algospace/util.py
algospace/version.txt
algospace.egg-info/PKG-INFO
algospace.egg-info/SOURCES.txt
algospace.egg-info/dependency_links.txt
algospace.egg-info/entry_points.txt
algospace.egg-info/requires.txt
algospace.egg-info/top_level.txt
algospace/customer/__init__.py
algospace/customer/config.py
algospace/customer/fn.py
algospace/customer/service.py
algospace/exceptions/__init__.py
algospace/provider/__init__.py
algospace/provider/cloud.py
algospace/provider/config.py
algospace/provider/config_generator.py
algospace/provider/config_loader.py
algospace/provider/docker_generator.py
algospace/provider/enroll.py
algospace/provider/param_validator.py
algospace/provider/service.py
algospace/provider/stdio.py
algospace/provider/templates/algospace-config.py
algospace/provider/templates/docker/algospace-docker-compose.yml
algospace/provider/templates/docker/algospace-docker-logs.sh
algospace/provider/templates/docker/algospace-docker-start.sh
algospace/provider/templates/docker/algospace-docker-stop.sh
algospace/provider/templates/docker/algospace-dockerfile