Metadata-Version: 2.1
Name: algospace
Version: 0.4.11
Summary: AlgoSpace: A platform for displaying and using algorithm achievements
Home-page: https://github.com/Algo-Space/algospace-pypi
Author: DBIIR
Author-email: ckeming@outlook.com
Maintainer: DBIIR
Maintainer-email: ckeming@outlook.com
License: BSD License
Project-URL: Documentation, https://algospace.top/publish
Project-URL: Homepage, https://algospace.top
Platform: all
Classifier: Development Status :: 4 - Beta
Classifier: Operating System :: OS Independent
Classifier: Intended Audience :: Developers
Classifier: License :: OSI Approved :: BSD License
Classifier: Programming Language :: Python
Classifier: Programming Language :: Python :: 3
Classifier: Programming Language :: Python :: 3.7
Classifier: Programming Language :: Python :: 3.8
Classifier: Programming Language :: Python :: 3.9
Classifier: Programming Language :: Python :: 3.10
Classifier: Programming Language :: Python :: 3.11
Classifier: Programming Language :: Python :: 3 :: Only
Classifier: Topic :: Software Development :: Libraries
Requires-Python: >=3.7
